mcp_server_tavily/__init__.py
mcp_server_tavily/__main__.py
mcp_server_tavily/server.py
mseep_mcp_tavily_proxy-0.1.4.dist-info/METADATA
mseep_mcp_tavily_proxy-0.1.4.dist-info/WHEEL
mseep_mcp_tavily_proxy-0.1.4.dist-info/entry_points.txt
mseep_mcp_tavily_proxy-0.1.4.dist-info/RECORD
